odoo/addons/purchase_internal_product_reference/README.rst
odoo/addons/purchase_internal_product_reference/__init__.py
odoo/addons/purchase_internal_product_reference/__manifest__.py
odoo/addons/purchase_internal_product_reference/i18n/es.po
odoo/addons/purchase_internal_product_reference/models/__init__.py
odoo/addons/purchase_internal_product_reference/models/product.py
odoo/addons/purchase_internal_product_reference/models/purchase_order_line.py
odoo/addons/purchase_internal_product_reference/models/res_company.py
odoo/addons/purchase_internal_product_reference/models/res_config_settings.py
odoo/addons/purchase_internal_product_reference/static/description/icon.png
odoo/addons/purchase_internal_product_reference/views/res_config_settings_view.xml
odoo_addon_purchase_internal_product_reference-15.0.1.0.0.2.dist-info/METADATA
odoo_addon_purchase_internal_product_reference-15.0.1.0.0.2.dist-info/WHEEL
odoo_addon_purchase_internal_product_reference-15.0.1.0.0.2.dist-info/top_level.txt
odoo_addon_purchase_internal_product_reference-15.0.1.0.0.2.dist-info/RECORD
