Metadata-Version: 2.1
Name: odoo-addon-purchase_internal_product_reference
Version: 15.0.1.0.0.2
Requires-Python: >=3.8
Requires-Dist: odoo>=15.0a,<15.1dev
Summary: Shows the internal product reference or the supplier's reference in purchasing
Home-page: https://github.com/sygel-technology/sy-purchase-workflow
License: AGPL-3
Author: Sygel, Odoo Community Association (OCA)
Author-email: support@odoo-community.org
Classifier: Programming Language :: Python
Classifier: Framework :: Odoo
Classifier: Framework :: Odoo :: 15.0
Classifier: License :: OSI Approved :: GNU Affero General Public License v3
